llsi/__init__.py
llsi/arx.py
llsi/controllerdesigner.py
llsi/figure.py
llsi/firor.py
llsi/ltimodel.py
llsi/math.py
llsi/matlab.py
llsi/pem.py
llsi/polynomialmodel.py
llsi/sklearn.py
llsi/statespacemodel.py
llsi/subspace.py
llsi/sysidalg.py
llsi/sysidalgbase.py
llsi/sysiddata.py
llsi/utils.py
llsi-0.5.0.dist-info/METADATA
llsi-0.5.0.dist-info/WHEEL
llsi-0.5.0.dist-info/licenses/LICENSE
llsi-0.5.0.dist-info/RECORD
