Metadata-Version: 2.4
Name: llsi
Version: 0.5.0
Summary: A lightweight linear system identification tool
Project-URL: Homepage, https://github.com/arminwitte/llsi
Project-URL: Bug Tracker, https://github.com/arminwitte/llsi/issues
Author: Armin Witte
License: MIT License
License-File: LICENSE
Keywords: system identification
Classifier: License :: OSI Approved :: MIT License
Classifier: Operating System :: OS Independent
Classifier: Programming Language :: Python :: 3
Requires-Python: >=3.8
Requires-Dist: matplotlib
Requires-Dist: numba
Requires-Dist: numpy>=1.19.0
Requires-Dist: pandas
Requires-Dist: scipy>=1.8.0
Requires-Dist: statsmodels>=0.14.1
Requires-Dist: tqdm
Provides-Extra: dev
Requires-Dist: build; extra == 'dev'
Requires-Dist: coverage; extra == 'dev'
Requires-Dist: pytest; extra == 'dev'
Requires-Dist: ruff; extra == 'dev'
Requires-Dist: scikit-learn; extra == 'dev'
Requires-Dist: twine; extra == 'dev'
Provides-Extra: sklearn
Requires-Dist: scikit-learn; extra == 'sklearn'
